cs/djutils.py
cs_djutils-20251231.dist-info/WHEEL
cs_djutils-20251231.dist-info/METADATA
cs_djutils-20251231.dist-info/RECORD
